<?xml version="1.0" ?>
<LOG_ROOT>
	<PROJECT NAME="lab7part3">
		<CBX_INST_ENTRY INSTANCE_NAME="|lab7part3|LPM_MUX:MUX_C" CBX_FILE_NAME="mux_p7e.tdf"/>
		<CBX_INST_ENTRY INSTANCE_NAME="|lab7part3|LPM_MUX:MUX_MDR" CBX_FILE_NAME="mux_p7e.tdf"/>
		<CBX_INST_ENTRY INSTANCE_NAME="|lab7part3|LPM_MUX:MUX_R1" CBX_FILE_NAME="mux_p7e.tdf"/>
		<CBX_INST_ENTRY INSTANCE_NAME="|lab7part3|LPM_COUNTER:PC" CBX_FILE_NAME="cntr_ckj.tdf"/>
		<CBX_INST_ENTRY INSTANCE_NAME="|lab7part3|LPM_COUNTER:SP" CBX_FILE_NAME="cntr_9ak.tdf"/>
		<CBX_INST_ENTRY INSTANCE_NAME="|lab7part3|LPM_MUX:MUX_D" CBX_FILE_NAME="mux_p7e.tdf"/>
		<CBX_INST_ENTRY INSTANCE_NAME="|lab7part3|LPM_MUX:MUX_MAR" CBX_FILE_NAME="mux_s7e.tdf"/>
		<CBX_INST_ENTRY INSTANCE_NAME="|lab7part3|f25lab7_useq:USeq|LPM_MUX:uPC_mux" CBX_FILE_NAME="mux_p7e.tdf"/>
		<CBX_INST_ENTRY INSTANCE_NAME="|lab7part3|f25lab7_useq:USeq|LPM_ROM:uROM|altrom:srom|altsyncram:rom_block" CBX_FILE_NAME="altsyncram_qsv.tdf"/>
		<CBX_INST_ENTRY INSTANCE_NAME="|lab7part3|LPM_ADD_SUB:ALU" CBX_FILE_NAME="add_sub_i9f.tdf"/>
		<CBX_INST_ENTRY INSTANCE_NAME="|lab7part3|LPM_MUX:MUX_M" CBX_FILE_NAME="mux_p7e.tdf"/>
		<CBX_INST_ENTRY INSTANCE_NAME="|lab7part3|LPM_MUX:MUX_R0" CBX_FILE_NAME="mux_p7e.tdf"/>
		<CBX_INST_ENTRY INSTANCE_NAME="|lab7part3|LPM_MUX:MUX_Z" CBX_FILE_NAME="mux_i7e.tdf"/>
		<CBX_INST_ENTRY INSTANCE_NAME="|lab7part3|LPM_RAM_DQ:MEMORY|altram:sram|altsyncram:ram_block" CBX_FILE_NAME="altsyncram_qu91.tdf"/>
	</PROJECT>
</LOG_ROOT>
